Naked/__init__.py
Naked/app.py
Naked/commandline.py
Naked/scratchpad.py
Naked/settings.py
Naked/commands/__init__.py
Naked/commands/args.py
Naked/commands/build.py
Naked/commands/classifier.py
Naked/commands/dist.py
Naked/commands/help.py
Naked/commands/locate.py
Naked/commands/make.py
Naked/commands/profile.py
Naked/commands/pyh.py
Naked/commands/test.py
Naked/commands/usage.py
Naked/commands/version.py
Naked/templates/__init__.py
Naked/templates/app_file.py
Naked/templates/licenses.py
Naked/templates/manifest_in_file.py
Naked/templates/profiler_file.py
Naked/templates/pypush_file.py
Naked/templates/readme_md_file.py
Naked/templates/settings_file.py
Naked/templates/setup_cfg_file.py
Naked/templates/setup_py_file.py
Naked/toolshed/__init__.py
Naked/toolshed/benchmarking.py
Naked/toolshed/casts.py
Naked/toolshed/file.py
Naked/toolshed/ink.py
Naked/toolshed/iter.py
Naked/toolshed/network.py
Naked/toolshed/python.py
Naked/toolshed/shell.py
Naked/toolshed/state.py
Naked/toolshed/system.py
Naked/toolshed/types.py
Naked/toolshed/c/__init__.py
Naked/toolshed/c/benchmarking.c
Naked/toolshed/c/benchmarking.pyx
Naked/toolshed/c/build.sh
Naked/toolshed/c/casts.c
Naked/toolshed/c/casts.pyx
Naked/toolshed/c/cstate.c
Naked/toolshed/c/cstate.pyx
Naked/toolshed/c/cythonize.sh
Naked/toolshed/c/file.c
Naked/toolshed/c/file.pyx
Naked/toolshed/c/ink.c
Naked/toolshed/c/ink.pyx
Naked/toolshed/c/network.c
Naked/toolshed/c/network.pyx
Naked/toolshed/c/python.c
Naked/toolshed/c/python.pyx
Naked/toolshed/c/setup.py
Naked/toolshed/c/shell.c
Naked/toolshed/c/shell.pyx
Naked/toolshed/c/system.c
Naked/toolshed/c/system.pyx
Naked/toolshed/c/types.c
Naked/toolshed/c/types.pyx
Naked-0.1.32.dist-info/METADATA
Naked-0.1.32.dist-info/WHEEL
Naked-0.1.32.dist-info/entry_points.txt
Naked-0.1.32.dist-info/top_level.txt
Naked-0.1.32.dist-info/RECORD
